{"stat.damageDealt":47490,"achievement.exploreAllBiomes":{"value":0,"progress":["Plains"]},"achievement.openInventory":69,"stat.fallOneCm":14448,"stat.flyOneCm":310025,"stat.killEntity.Chicken":39,"stat.damageTaken":25545,"stat.timeSinceDeath":5,"stat.playOneMinute":47271,"stat.leaveGame":6,"stat.diveOneCm":145,"stat.entityKilledBy.Skeleton":2,"stat.deaths":17,"stat.jump":235,"stat.swimOneCm":680,"stat.mobKills":289,"stat.entityKilledBy.Zombie":14,"stat.killEntity.Skeleton":9,"stat.walkOneCm":530171,"stat.killEntity.Zombie":241}