{"stat.damageDealt":7275,"stat.crouchOneCm":97,"stat.beaconInteraction":2,"achievement.exploreAllBiomes":{"value":0,"progress":["Plains"]},"stat.craftingTableInteraction":1,"achievement.openInventory":13,"stat.craftItem.minecraft.wooden_shovel":1,"stat.breakItem.minecraft.wooden_sword":1,"stat.talkedToVillager":28,"stat.flyOneCm":23687,"stat.killEntity.Chicken":24,"stat.damageTaken":1280,"stat.timeSinceDeath":5437,"stat.leaveGame":1,"stat.playOneMinute":19127,"stat.useItem.minecraft.chicken":1,"stat.craftItem.minecraft.paper":1,"stat.jump":86,"stat.deaths":4,"stat.useItem.minecraft.wooden_sword":138,"stat.craftItem.minecraft.wooden_sword":1,"stat.mobKills":40,"stat.entityKilledBy.Zombie":3,"stat.walkOneCm":181898,"stat.killEntity.Zombie":16,"stat.chestOpened":10,"stat.sprintOneCm":62830,"stat.tradedWithVillager":9}