{"stat.crouchOneCm":758,"stat.beaconInteraction":1,"stat.breakItem.minecraft.leather_boots":1,"stat.craftItem.minecraft.wooden_hoe":1,"stat.entityKilledBy.Guardian":1,"stat.enderchestOpened":2,"achievement.openInventory":90,"stat.damageDealt":17180,"achievement.exploreAllBiomes":{"value":0,"progress":["Plains"]},"stat.craftItem.minecraft.bread":3,"stat.craftItem.minecraft.wooden_shovel":1,"stat.talkedToVillager":79,"stat.breakItem.minecraft.wooden_sword":2,"stat.fallOneCm":11171,"stat.flyOneCm":213612,"stat.climbOneCm":1060,"stat.craftItem.minecraft.book":1,"stat.killEntity.Chicken":51,"stat.damageTaken":5472,"stat.timeSinceDeath":44,"stat.useItem.minecraft.cooked_porkchop":1,"stat.craftItem.minecraft.leather_chestplate":1,"stat.leaveGame":2,"stat.diveOneCm":5531,"stat.craftItem.minecraft.iron_ingot":1,"stat.craftItem.minecraft.paper":2,"stat.playOneMinute":43466,"stat.killEntity.Rabbit":3,"stat.entityKilledBy.Skeleton":1,"stat.deaths":10,"stat.craftItem.minecraft.leather_leggings":1,"stat.swimOneCm":943,"stat.mobKills":97,"stat.breakItem.minecraft.leather_helmet":1,"stat.walkOneCm":329779,"stat.playerKills":1,"stat.killEntity.Zombie":43,"stat.chestOpened":12,"stat.tradedWithVillager":30,"stat.useItem.minecraft.bread":3,"stat.jump":600,"stat.craftItem.minecraft.brick":10,"stat.useItem.minecraft.wooden_sword":332,"stat.craftItem.minecraft.wooden_sword":2,"stat.useItem.minecraft.pumpkin_pie":4,"stat.entityKilledBy.Zombie":8,"stat.useItem.minecraft.wooden_shovel":3,"stat.sprintOneCm":248405}