{"stat.damageDealt":5900,"stat.crouchOneCm":470,"achievement.exploreAllBiomes":{"value":0,"progress":["Plains"]},"achievement.openInventory":33,"stat.craftItem.minecraft.wooden_shovel":1,"stat.talkedToVillager":19,"stat.fallOneCm":1899,"stat.flyOneCm":72164,"stat.killEntity.Chicken":46,"stat.damageTaken":1480,"stat.timeSinceDeath":7060,"stat.playOneMinute":50348,"stat.craftItem.minecraft.leather_chestplate":1,"stat.leaveGame":6,"stat.craftItem.minecraft.paper":1,"stat.deaths":5,"stat.craftItem.minecraft.brick":47,"stat.jump":234,"stat.useItem.minecraft.wooden_sword":118,"stat.craftItem.minecraft.wooden_sword":1,"stat.mobKills":46,"stat.entityKilledBy.Zombie":3,"stat.walkOneCm":235803,"stat.chestOpened":19,"stat.sprintOneCm":104595,"stat.tradedWithVillager":44,"stat.useItem.minecraft.bread":10}