{"stat.crouchOneCm":143,"stat.damageDealt":550,"achievement.exploreAllBiomes":{"value":0,"progress":["Plains"]},"achievement.openInventory":1,"stat.talkedToVillager":6,"stat.fallOneCm":211,"stat.flyOneCm":2032,"stat.killEntity.Chicken":4,"stat.timeSinceDeath":2283,"stat.leaveGame":1,"stat.playOneMinute":2283,"stat.jump":8,"stat.useItem.minecraft.wooden_sword":11,"stat.craftItem.minecraft.wooden_sword":1,"stat.mobKills":4,"stat.walkOneCm":14579,"stat.sprintOneCm":3874,"stat.tradedWithVillager":2}