{"stat.damageDealt":725,"stat.crouchOneCm":593,"achievement.exploreAllBiomes":{"value":0,"progress":["Plains"]},"achievement.openInventory":4,"stat.talkedToVillager":12,"stat.fallOneCm":211,"stat.flyOneCm":3049,"stat.killEntity.Chicken":3,"stat.damageTaken":200,"stat.timeSinceDeath":4834,"stat.playOneMinute":5133,"stat.leaveGame":2,"stat.deaths":1,"stat.jump":12,"stat.useItem.minecraft.wooden_sword":14,"stat.craftItem.minecraft.wooden_sword":1,"stat.mobKills":3,"stat.walkOneCm":38531,"stat.sprintOneCm":3030,"stat.tradedWithVillager":2}