{"stat.crouchOneCm":101,"stat.damageDealt":6840,"achievement.exploreAllBiomes":{"value":0,"progress":["Plains"]},"stat.entityKilledBy.Guardian":1,"achievement.openInventory":14,"stat.breakItem.minecraft.wooden_sword":2,"stat.talkedToVillager":14,"stat.fallOneCm":2110,"stat.flyOneCm":58961,"stat.climbOneCm":114,"stat.killEntity.Chicken":23,"stat.damageTaken":1855,"stat.timeSinceDeath":64,"stat.playOneMinute":15964,"stat.leaveGame":2,"stat.diveOneCm":2419,"stat.killEntity.Rabbit":1,"stat.craftItem.minecraft.iron_ingot":1,"stat.deaths":4,"stat.swimOneCm":620,"stat.furnaceInteraction":1,"stat.mobKills":35,"stat.walkOneCm":148169,"stat.killEntity.Zombie":10,"stat.chestOpened":4,"stat.tradedWithVillager":6,"stat.useItem.minecraft.bread":6,"stat.jump":220,"stat.useItem.minecraft.wooden_sword":65,"stat.entityKilledBy.Zombie":2,"stat.useItem.minecraft.wooden_shovel":17,"stat.killEntity.Guardian":1,"stat.sprintOneCm":56600}