{"stat.damageDealt":12125,"achievement.exploreAllBiomes":{"value":0,"progress":["Plains"]},"stat.craftItem.minecraft.wooden_hoe":2,"achievement.openInventory":34,"stat.craftItem.minecraft.wooden_shovel":1,"stat.breakItem.minecraft.wooden_sword":2,"stat.talkedToVillager":58,"stat.fallOneCm":1593,"stat.flyOneCm":74676,"stat.craftItem.minecraft.book":1,"stat.killEntity.Chicken":55,"stat.damageTaken":3310,"stat.timeSinceDeath":30,"stat.useItem.minecraft.cooked_porkchop":1,"stat.leaveGame":1,"stat.craftItem.minecraft.cooked_porkchop":1,"stat.craftItem.minecraft.iron_ingot":1,"stat.craftItem.minecraft.paper":2,"stat.playOneMinute":54908,"stat.killEntity.Rabbit":13,"stat.deaths":9,"stat.furnaceInteraction":1,"stat.mobKills":147,"stat.walkOneCm":540227,"stat.killEntity.Zombie":79,"stat.chestOpened":3,"stat.tradedWithVillager":73,"stat.craftItem.minecraft.brick":86,"stat.jump":367,"stat.useItem.minecraft.wooden_sword":229,"stat.craftItem.minecraft.wooden_sword":3,"stat.entityKilledBy.Zombie":9,"stat.useItem.minecraft.wooden_shovel":18,"stat.sprintOneCm":223848}