{"stat.damageDealt":15615,"achievement.exploreAllBiomes":{"value":0,"progress":["Plains"]},"achievement.openInventory":89,"stat.fallOneCm":12278,"stat.flyOneCm":86860,"stat.useItem.269":14,"stat.craftItem.272":1,"stat.breakItem.299":1,"stat.craftItem.339":1,"stat.craftItem.336":27,"stat.killEntity.Chicken":43,"stat.damageTaken":21595,"stat.playOneMinute":82853,"stat.leaveGame":3,"stat.breakItem.301":2,"stat.breakItem.300":2,"stat.useItem.272":42,"stat.craftItem.269":1,"stat.breakItem.298":2,"stat.deaths":10,"stat.jump":587,"stat.swimOneCm":430,"stat.useItem.268":249,"stat.mobKills":97,"stat.craftItem.268":3,"stat.entityKilledBy.Zombie":10,"stat.walkOneCm":560118,"stat.killEntity.Zombie":54,"stat.breakItem.268":3}