{"stat.damageDealt":2985,"stat.crouchOneCm":20,"achievement.exploreAllBiomes":{"value":0,"progress":["Plains"]},"achievement.openInventory":5,"stat.trappedChestTriggered":4,"stat.enderchestOpened":1,"stat.talkedToVillager":13,"stat.fallOneCm":3889,"stat.flyOneCm":36719,"stat.killEntity.Chicken":22,"stat.damageTaken":11,"stat.timeSinceDeath":9764,"stat.leaveGame":1,"stat.playOneMinute":9764,"stat.craftItem.minecraft.paper":1,"stat.jump":169,"stat.useItem.minecraft.wooden_sword":58,"stat.craftItem.minecraft.wooden_sword":1,"stat.mobKills":22,"stat.walkOneCm":96378,"stat.chestOpened":6,"stat.sprintOneCm":77897,"stat.tradedWithVillager":5,"stat.useItem.minecraft.bread":6}