{"stat.damageDealt":975,"achievement.openInventory":1,"achievement.exploreAllBiomes":{"value":0,"progress":["Plains"]},"stat.talkedToVillager":9,"stat.fallOneCm":844,"stat.flyOneCm":9977,"stat.killEntity.Chicken":3,"stat.timeSinceDeath":5163,"stat.leaveGame":1,"stat.playOneMinute":5163,"stat.jump":39,"stat.useItem.minecraft.wooden_sword":19,"stat.craftItem.minecraft.wooden_sword":1,"stat.mobKills":5,"stat.walkOneCm":25692,"stat.killEntity.Zombie":2,"stat.chestOpened":5,"stat.sprintOneCm":8288,"stat.tradedWithVillager":2}