{"stat.damageDealt":3410,"achievement.exploreAllBiomes":{"value":0,"progress":["Plains"]},"achievement.openInventory":9,"stat.craftItem.minecraft.wooden_shovel":1,"stat.breakItem.minecraft.wooden_sword":1,"stat.talkedToVillager":15,"stat.fallOneCm":633,"stat.flyOneCm":21526,"stat.killEntity.Chicken":21,"stat.damageTaken":270,"stat.timeSinceDeath":131,"stat.playOneMinute":7378,"stat.leaveGame":4,"stat.craftItem.minecraft.paper":1,"stat.deaths":1,"stat.mobKills":24,"stat.walkOneCm":79061,"stat.killEntity.Zombie":3,"stat.chestOpened":3,"stat.tradedWithVillager":7,"stat.useItem.minecraft.bread":1,"stat.jump":22,"stat.useItem.minecraft.wooden_sword":67,"stat.craftItem.minecraft.wooden_sword":1,"stat.entityKilledBy.Zombie":1,"stat.useItem.minecraft.wooden_shovel":3,"stat.sprintOneCm":41240}