{
    "__filename__": "./server/skylife.json",
    "name": "skylife",
    "createDate": "2018-9-15 22:02:24",
    "lastDate": "2018-10-4 22:28:16",
    "ie": "UTF-8",
    "oe": "UTF-8",
    "autoRestart": false,
    "schedule": [],
    "addCmd": [
        ""
    ],
    "java": "java",
    "jarName": "spigot-1.12.2-R0.1-SNAPSHOT-b1648.jar",
    "Xmx": "",
    "Xms": "",
    "cwd": "./server1/空岛生存",
    "highCommande": "java -Xmx512M -Xms512M -Dfile.encoding=UTF-8 -jar spigot-1.12.2-R0.1-SNAPSHOT-b1648.jar nogui",
    "run": false,
    "serverName": "skylife"
}